{
  "HouseStyle": [
    {
      "min": 104000.0,
      "q1": 164250.0,
      "median": 194000.0,
      "q3": 223750.0,
      "max": 295000.0,
      "outliers": [
        475000.0
      ],
      "n_outliers": 1,
      "category": "2.5Fin",
      "n": 8
    },
    {
      "min": 40000.0,
      "q1": 159500.0,
      "median": 190000.0,
      "q3": 240000.0,
      "max": 359100.0,
      "outliers": [
        438780.0,
        383970.0,
        412500.0,
        403000.0,
        437154.0,
        426000.0,
        380000.0,
        446261.0,
        451950.0,
        402000.0,
        755000.0,
        361919.0,
        538000.0,
        485000.0,
        582933.0,
        556581.0,
        424870.0,
        625000.0,
        745000.0
      ],
      "n_outliers": 19,
      "category": "2Story",
      "n": 445
    },
    {
      "min": 107000.0,
      "q1": 145000.0,
      "median": 164500.0,
      "q3": 178000.0,
      "max": 197900.0,
      "outliers": [
        91000.0,
        242000.0,
        275000.0,
        345000.0,
        274970.0
      ],
      "n_outliers": 5,
      "category": "SLvl",
      "n": 65
    },
    {
      "min": 34900.0,
      "q1": 127000.0,
      "median": 154750.0,
      "q3": 209350.0,
      "max": 328900.0,
      "outliers": [
        385000.0,
        372402.0,
        501837.0,
        386250.0,
        415298.0,
        360000.0,
        375000.0,
        377426.0,
        394432.0,
        555000.0,
        440000.0,
        374000.0,
        430000.0,
        402861.0,
        369900.0,
        370878.0,
        350000.0,
        423000.0,
        372500.0,
        392000.0,
        395000.0,
        385000.0,
        611657.0,
        395192.0,
        337500.0,
        392500.0,
        367294.0,
        465000.0,
        378500.0,
        335000.0,
        466500.0,
        377500.0,
        394617.0
      ],
      "n_outliers": 33,
      "category": "1Story",
      "n": 726
    },
    {
      "min": 108959.0,
      "q1": 127500.0,
      "median": 135960.0,
      "q3": 148000.0,
      "max": 178400.0,
      "outliers": [
        198500.0,
        206300.0,
        81000.0,
        86000.0,
        75500.0,
        84500.0,
        80000.0,
        92000.0
      ],
      "n_outliers": 8,
      "category": "SFoyer",
      "n": 37
    },
    {
      "min": 101000.0,
      "q1": 125000.0,
      "median": 133900.0,
      "q3": 163500.0,
      "max": 214500.0,
      "outliers": [
        325000.0
      ],
      "n_outliers": 1,
      "category": "2.5Unf",
      "n": 11
    },
    {
      "min": 66500.0,
      "q1": 114625.0,
      "median": 132000.0,
      "q3": 159325.5,
      "max": 225000.0,
      "outliers": [
        239686.0,
        311500.0,
        277000.0,
        228950.0,
        229000.0,
        316600.0,
        240000.0,
        250000.0,
        37900.0,
        285000.0,
        381000.0,
        256000.0,
        410000.0
      ],
      "n_outliers": 13,
      "category": "1.5Fin",
      "n": 154
    },
    {
      "min": 76000.0,
      "q1": 98175.0,
      "median": 111250.0,
      "q3": 120500.0,
      "max": 139400.0,
      "outliers": [],
      "n_outliers": 0,
      "category": "1.5Unf",
      "n": 14
    }
  ],
  "GarageType": [
    {
      "min": 91000.0,
      "q1": 180750.0,
      "median": 227500.0,
      "q3": 300719.25,
      "max": 451950.0,
      "outliers": [
        538000.0,
        485000.0,
        582933.0,
        556581.0
      ],
      "n_outliers": 4,
      "category": "BuiltIn",
      "n": 88
    },
    {
      "min": 60000.0,
      "q1": 150000.0,
      "median": 185000.0,
      "q3": 235000.0,
      "max": 360000.0,
      "outliers": [
        385000.0,
        372402.0,
        501837.0,
        386250.0,
        403000.0,
        415298.0,
        375000.0,
        377426.0,
        437154.0,
        394432.0,
        555000.0,
        440000.0,
        374000.0,
        430000.0,
        402861.0,
        446261.0,
        369900.0,
        370878.0,
        402000.0,
        423000.0,
        372500.0,
        392000.0,
        755000.0,
        395000.0,
        385000.0,
        611657.0,
        395192.0,
        625000.0,
        392500.0,
        745000.0,
        367294.0,
        465000.0,
        378500.0,
        410000.0,
        466500.0,
        377500.0,
        394617.0
      ],
      "n_outliers": 37,
      "category": "Attchd",
      "n": 870
    },
    {
      "min": 145000.0,
      "q1": 146250.0,
      "median": 159000.0,
      "q3": 170250.0,
      "max": 186700.0,
      "outliers": [
        87000.0
      ],
      "n_outliers": 1,
      "category": "2Types",
      "n": 6
    },
    {
      "min": 83000.0,
      "q1": 132250.0,
      "median": 148000.0,
      "q3": 174000.0,
      "max": 235000.0,
      "outliers": [
        359100.0,
        55993.0
      ],
      "n_outliers": 2,
      "category": "Basment",
      "n": 19
    },
    {
      "min": 58500.0,
      "q1": 110000.0,
      "median": 129500.0,
      "q3": 147700.0,
      "max": 200100.0,
      "outliers": [
        40000.0,
        259500.0,
        475000.0,
        315000.0,
        235000.0,
        205000.0,
        239000.0,
        214500.0,
        239000.0,
        234000.0,
        210000.0,
        325000.0,
        265979.0,
        240000.0,
        35311.0,
        220000.0,
        224000.0,
        239000.0,
        230000.0,
        256000.0,
        274300.0,
        207000.0
      ],
      "n_outliers": 22,
      "category": "Detchd",
      "n": 387
    },
    {
      "min": 82000.0,
      "q1": 95000.0,
      "median": 108000.0,
      "q3": 110000.0,
      "max": 129000.0,
      "outliers": [
        164900.0
      ],
      "n_outliers": 1,
      "category": "CarPort",
      "n": 9
    }
  ],
  "SaleCondition": [
    {
      "min": 113000.0,
      "q1": 193879.0,
      "median": 244600.0,
      "q3": 339750.0,
      "max": 556581.0,
      "outliers": [
        582933.0,
        611657.0
      ],
      "n_outliers": 2,
      "category": "Partial",
      "n": 125
    },
    {
      "min": 39300.0,
      "q1": 130000.0,
      "median": 160000.0,
      "q3": 205000.0,
      "max": 317000.0,
      "outliers": [
        319900.0,
        385000.0,
        320000.0,
        412500.0,
        475000.0,
        386250.0,
        403000.0,
        360000.0,
        375000.0,
        354000.0,
        324000.0,
        377426.0,
        340000.0,
        555000.0,
        380000.0,
        326000.0,
        374000.0,
        430000.0,
        325000.0,
        325000.0,
        451950.0,
        345000.0,
        350000.0,
        402000.0,
        755000.0,
        335000.0,
        341000.0,
        320000.0,
        337000.0,
        538000.0,
        350000.0,
        320000.0,
        336000.0,
        348000.0,
        337500.0,
        335000.0,
        328000.0,
        325000.0,
        625000.0,
        378500.0,
        381000.0,
        325000.0,
        335000.0,
        333168.0,
        410000.0,
        466500.0,
        377500.0,
        340000.0
      ],
      "n_outliers": 48,
      "category": "Normal",
      "n": 1198
    },
    {
      "min": 55993.0,
      "q1": 116383.25,
      "median": 148145.0,
      "q3": 202043.0,
      "max": 274970.0,
      "outliers": [
        359100.0
      ],
      "n_outliers": 1,
      "category": "Alloca",
      "n": 12
    },
    {
      "min": 82500.0,
      "q1": 115500.0,
      "median": 140500.0,
      "q3": 170250.0,
      "max": 235000.0,
      "outliers": [
        259000.0
      ],
      "n_outliers": 1,
      "category": "Family",
      "n": 20
    },
    {
      "min": 34900.0,
      "q1": 104000.0,
      "median": 130000.0,
      "q3": 172500.0,
      "max": 258000.0,
      "outliers": [
        290000.0,
        328900.0,
        287000.0,
        310000.0,
        745000.0
      ],
      "n_outliers": 5,
      "category": "Abnorml",
      "n": 101
    },
    {
      "min": 81000.0,
      "q1": 81750.0,
      "median": 104000.0,
      "q3": 126375.0,
      "max": 127500.0,
      "outliers": [],
      "n_outliers": 0,
      "category": "AdjLand",
      "n": 4
    }
  ],
  "MSZoning": [
    {
      "min": 144152.0,
      "q1": 174000.0,
      "median": 205950.0,
      "q3": 250000.0,
      "max": 340000.0,
      "outliers": [
        370878.0
      ],
      "n_outliers": 1,
      "category": "FV",
      "n": 65
    },
    {
      "min": 39300.0,
      "q1": 137700.0,
      "median": 174000.0,
      "q3": 224700.0,
      "max": 354000.0,
      "outliers": [
        385000.0,
        438780.0,
        383970.0,
        372402.0,
        412500.0,
        501837.0,
        386250.0,
        403000.0,
        415298.0,
        360000.0,
        375000.0,
        377426.0,
        437154.0,
        394432.0,
        426000.0,
        555000.0,
        440000.0,
        380000.0,
        374000.0,
        430000.0,
        402861.0,
        446261.0,
        369900.0,
        451950.0,
        359100.0,
        402000.0,
        423000.0,
        372500.0,
        392000.0,
        755000.0,
        361919.0,
        538000.0,
        395000.0,
        485000.0,
        582933.0,
        385000.0,
        611657.0,
        395192.0,
        556581.0,
        424870.0,
        625000.0,
        745000.0,
        367294.0,
        465000.0,
        378500.0,
        381000.0,
        410000.0,
        466500.0,
        377500.0,
        394617.0
      ],
      "n_outliers": 50,
      "category": "RL",
      "n": 1151
    },
    {
      "min": 76000.0,
      "q1": 106150.0,
      "median": 136500.0,
      "q3": 148608.5,
      "max": 200000.0,
      "outliers": [],
      "n_outliers": 0,
      "category": "RH",
      "n": 16
    },
    {
      "min": 52500.0,
      "q1": 100000.0,
      "median": 120500.0,
      "q3": 140000.0,
      "max": 200000.0,
      "outliers": [
        475000.0,
        235000.0,
        295000.0,
        207000.0,
        206300.0,
        325000.0,
        265979.0,
        37900.0,
        392500.0,
        256000.0,
        275000.0
      ],
      "n_outliers": 11,
      "category": "RM",
      "n": 218
    },
    {
      "min": 34900.0,
      "q1": 43998.25,
      "median": 74700.0,
      "q3": 98332.0,
      "max": 133900.0,
      "outliers": [],
      "n_outliers": 0,
      "category": "C (all)",
      "n": 10
    }
  ],
  "BldgType": [
    {
      "min": 75500.0,
      "q1": 143187.5,
      "median": 172200.0,
      "q3": 207375.0,
      "max": 286000.0,
      "outliers": [
        319900.0,
        324000.0,
        318061.0,
        328900.0,
        392500.0,
        367294.0
      ],
      "n_outliers": 6,
      "category": "TwnhsE",
      "n": 114
    },
    {
      "min": 34900.0,
      "q1": 131475.0,
      "median": 167900.0,
      "q3": 222000.0,
      "max": 354000.0,
      "outliers": [
        385000.0,
        438780.0,
        383970.0,
        372402.0,
        412500.0,
        501837.0,
        475000.0,
        386250.0,
        403000.0,
        415298.0,
        360000.0,
        375000.0,
        377426.0,
        437154.0,
        394432.0,
        426000.0,
        555000.0,
        440000.0,
        380000.0,
        374000.0,
        430000.0,
        402861.0,
        446261.0,
        369900.0,
        451950.0,
        359100.0,
        370878.0,
        402000.0,
        423000.0,
        372500.0,
        392000.0,
        755000.0,
        361919.0,
        538000.0,
        395000.0,
        485000.0,
        582933.0,
        385000.0,
        611657.0,
        395192.0,
        556581.0,
        424870.0,
        625000.0,
        745000.0,
        465000.0,
        378500.0,
        381000.0,
        410000.0,
        466500.0,
        377500.0,
        394617.0
      ],
      "n_outliers": 51,
      "category": "1Fam",
      "n": 1220
    },
    {
      "min": 75000.0,
      "q1": 95750.0,
      "median": 137500.0,
      "q3": 168750.0,
      "max": 230000.0,
      "outliers": [],
      "n_outliers": 0,
      "category": "Twnhs",
      "n": 43
    },
    {
      "min": 82000.0,
      "q1": 118375.0,
      "median": 135980.0,
      "q3": 145000.0,
      "max": 179000.0,
      "outliers": [
        206300.0,
        188000.0,
        190000.0,
        200000.0
      ],
      "n_outliers": 4,
      "category": "Duplex",
      "n": 52
    },
    {
      "min": 55000.0,
      "q1": 106875.0,
      "median": 127500.0,
      "q3": 142500.0,
      "max": 168000.0,
      "outliers": [
        228950.0,
        200000.0
      ],
      "n_outliers": 2,
      "category": "2fmCon",
      "n": 31
    }
  ],
  "Foundation": [
    {
      "min": 78000.0,
      "q1": 173000.0,
      "median": 205000.0,
      "q3": 262140.0,
      "max": 395192.0,
      "outliers": [
        438780.0,
        412500.0,
        501837.0,
        403000.0,
        415298.0,
        437154.0,
        426000.0,
        555000.0,
        440000.0,
        430000.0,
        446261.0,
        451950.0,
        402000.0,
        423000.0,
        755000.0,
        538000.0,
        485000.0,
        582933.0,
        611657.0,
        556581.0,
        424870.0,
        625000.0,
        745000.0,
        465000.0,
        410000.0,
        466500.0
      ],
      "n_outliers": 26,
      "category": "PConc",
      "n": 647
    },
    {
      "min": 143000.0,
      "q1": 153500.0,
      "median": 164000.0,
      "q3": 207000.0,
      "max": 250000.0,
      "outliers": [],
      "n_outliers": 0,
      "category": "Wood",
      "n": 3
    },
    {
      "min": 55993.0,
      "q1": 122125.0,
      "median": 141500.0,
      "q3": 168000.0,
      "max": 235000.0,
      "outliers": [
        385000.0,
        244000.0,
        260000.0,
        259500.0,
        243000.0,
        315000.0,
        277000.0,
        311500.0,
        241500.0,
        277000.0,
        241500.0,
        375000.0,
        260000.0,
        301000.0,
        242000.0,
        280000.0,
        256000.0,
        34900.0,
        289000.0,
        402861.0,
        316600.0,
        240000.0,
        345000.0,
        302000.0,
        52000.0,
        299800.0,
        250000.0,
        250000.0,
        35311.0,
        242000.0,
        244400.0,
        272000.0,
        287000.0,
        271900.0,
        244000.0,
        294000.0,
        381000.0,
        52500.0,
        262500.0,
        237500.0,
        250000.0,
        274970.0
      ],
      "n_outliers": 42,
      "category": "CBlock",
      "n": 634
    },
    {
      "min": 102776.0,
      "q1": 109625.0,
      "median": 126500.0,
      "q3": 233734.25,
      "max": 266500.0,
      "outliers": [],
      "n_outliers": 0,
      "category": "Stone",
      "n": 6
    },
    {
      "min": 37900.0,
      "q1": 102400.0,
      "median": 125250.0,
      "q3": 151250.0,
      "max": 214500.0,
      "outliers": [
        475000.0,
        295000.0,
        239000.0,
        234000.0,
        325000.0,
        240000.0,
        239000.0,
        256000.0
      ],
      "n_outliers": 8,
      "category": "BrkTil",
      "n": 146
    },
    {
      "min": 55000.0,
      "q1": 89375.0,
      "median": 104150.0,
      "q3": 118884.5,
      "max": 144000.0,
      "outliers": [
        198500.0,
        39300.0,
        169000.0
      ],
      "n_outliers": 3,
      "category": "Slab",
      "n": 24
    }
  ],
  "SaleType": [
    {
      "min": 113000.0,
      "q1": 194050.25,
      "median": 247453.0,
      "q3": 341919.75,
      "max": 556581.0,
      "outliers": [
        582933.0,
        611657.0
      ],
      "n_outliers": 2,
      "category": "New",
      "n": 122
    },
    {
      "min": 136000.0,
      "q1": 152500.0,
      "median": 188750.0,
      "q3": 246850.0,
      "max": 328900.0,
      "outliers": [],
      "n_outliers": 0,
      "category": "CWD",
      "n": 4
    },
    {
      "min": 34900.0,
      "q1": 128925.0,
      "median": 158000.0,
      "q3": 202950.0,
      "max": 313000.0,
      "outliers": [
        319900.0,
        385000.0,
        317000.0,
        320000.0,
        412500.0,
        475000.0,
        315000.0,
        386250.0,
        403000.0,
        360000.0,
        375000.0,
        354000.0,
        377426.0,
        340000.0,
        315000.0,
        555000.0,
        380000.0,
        326000.0,
        374000.0,
        430000.0,
        315750.0,
        315000.0,
        325000.0,
        316600.0,
        325000.0,
        359100.0,
        345000.0,
        350000.0,
        402000.0,
        755000.0,
        335000.0,
        341000.0,
        320000.0,
        337000.0,
        538000.0,
        350000.0,
        320000.0,
        336000.0,
        348000.0,
        337500.0,
        315500.0,
        335000.0,
        328000.0,
        325000.0,
        625000.0,
        745000.0,
        378500.0,
        381000.0,
        325000.0,
        335000.0,
        333168.0,
        410000.0,
        315000.0,
        466500.0,
        377500.0,
        340000.0
      ],
      "n_outliers": 56,
      "category": "WD",
      "n": 1267
    },
    {
      "min": 60000.0,
      "q1": 95000.0,
      "median": 144000.0,
      "q3": 207500.0,
      "max": 212000.0,
      "outliers": [],
      "n_outliers": 0,
      "category": "ConLw",
      "n": 5
    },
    {
      "min": 79900.0,
      "q1": 85000.0,
      "median": 140000.0,
      "q3": 160000.0,
      "max": 235128.0,
      "outliers": [],
      "n_outliers": 0,
      "category": "ConLD",
      "n": 9
    },
    {
      "min": 60000.0,
      "q1": 112000.0,
      "median": 139000.0,
      "q3": 160500.0,
      "max": 217000.0,
      "outliers": [
        244400.0,
        287000.0,
        257000.0
      ],
      "n_outliers": 3,
      "category": "COD",
      "n": 43
    },
    {
      "min": 110000.0,
      "q1": 115000.0,
      "median": 125000.0,
      "q3": 200000.0,
      "max": 200000.0,
      "outliers": [
        451950.0
      ],
      "n_outliers": 1,
      "category": "ConLI",
      "n": 5
    },
    {
      "min": 93500.0,
      "q1": 104775.0,
      "median": 116050.0,
      "q3": 133025.0,
      "max": 150000.0,
      "outliers": [],
      "n_outliers": 0,
      "category": "Oth",
      "n": 3
    }
  ],
  "RoofStyle": [
    {
      "min": 82000.0,
      "q1": 143000.0,
      "median": 185000.0,
      "q3": 242000.0,
      "max": 274970.0,
      "outliers": [],
      "n_outliers": 0,
      "category": "Flat",
      "n": 13
    },
    {
      "min": 55000.0,
      "q1": 139675.0,
      "median": 176500.0,
      "q3": 277875.0,
      "max": 485000.0,
      "outliers": [
        501837.0,
        555000.0,
        538000.0,
        582933.0,
        611657.0,
        556581.0,
        625000.0,
        745000.0
      ],
      "n_outliers": 8,
      "category": "Hip",
      "n": 286
    },
    {
      "min": 100000.0,
      "q1": 145500.0,
      "median": 175000.0,
      "q3": 216000.0,
      "max": 265979.0,
      "outliers": [],
      "n_outliers": 0,
      "category": "Mansard",
      "n": 7
    },
    {
      "min": 34900.0,
      "q1": 128000.0,
      "median": 160000.0,
      "q3": 202500.0,
      "max": 311500.0,
      "outliers": [
        325300.0,
        385000.0,
        317000.0,
        383970.0,
        320000.0,
        412500.0,
        325624.0,
        475000.0,
        403000.0,
        415298.0,
        360000.0,
        342643.0,
        354000.0,
        324000.0,
        340000.0,
        426000.0,
        339750.0,
        315000.0,
        440000.0,
        315750.0,
        316600.0,
        325000.0,
        451950.0,
        319000.0,
        359100.0,
        345000.0,
        370878.0,
        423000.0,
        392000.0,
        755000.0,
        337000.0,
        328900.0,
        348000.0,
        335000.0,
        328000.0,
        325000.0,
        465000.0,
        381000.0,
        335000.0,
        333168.0,
        377500.0,
        340000.0
      ],
      "n_outliers": 42,
      "category": "Gable",
      "n": 1141
    },
    {
      "min": 40000.0,
      "q1": 105500.0,
      "median": 139000.0,
      "q3": 193750.0,
      "max": 259500.0,
      "outliers": [],
      "n_outliers": 0,
      "category": "Gambrel",
      "n": 11
    }
  ],
  "MSSubClass": [
    {
      "min": 129000.0,
      "q1": 185000.0,
      "median": 215200.0,
      "q3": 268750.0,
      "max": 383970.0,
      "outliers": [
        438780.0,
        412500.0,
        403000.0,
        437154.0,
        426000.0,
        446261.0,
        451950.0,
        402000.0,
        755000.0,
        538000.0,
        485000.0,
        582933.0,
        556581.0,
        424870.0,
        625000.0,
        745000.0
      ],
      "n_outliers": 16,
      "category": "60",
      "n": 299
    },
    {
      "min": 99500.0,
      "q1": 158050.0,
      "median": 192000.0,
      "q3": 232000.0,
      "max": 328900.0,
      "outliers": [
        392500.0,
        367294.0
      ],
      "n_outliers": 2,
      "category": "120",
      "n": 87
    },
    {
      "min": 107000.0,
      "q1": 147250.0,
      "median": 166500.0,
      "q3": 179425.0,
      "max": 197900.0,
      "outliers": [
        242000.0,
        275000.0,
        345000.0,
        274970.0
      ],
      "n_outliers": 4,
      "category": "80",
      "n": 58
    },
    {
      "min": 101000.0,
      "q1": 125625.0,
      "median": 163500.0,
      "q3": 219625.0,
      "max": 325000.0,
      "outliers": [
        475000.0
      ],
      "n_outliers": 1,
      "category": "75",
      "n": 16
    },
    {
      "min": 35311.0,
      "q1": 132500.0,
      "median": 159250.0,
      "q3": 220000.0,
      "max": 350000.0,
      "outliers": [
        385000.0,
        372402.0,
        501837.0,
        386250.0,
        415298.0,
        360000.0,
        375000.0,
        377426.0,
        394432.0,
        555000.0,
        440000.0,
        374000.0,
        430000.0,
        402861.0,
        369900.0,
        370878.0,
        423000.0,
        372500.0,
        392000.0,
        395000.0,
        385000.0,
        611657.0,
        395192.0,
        465000.0,
        378500.0,
        466500.0,
        377500.0,
        394617.0
      ],
      "n_outliers": 28,
      "category": "20",
      "n": 536
    },
    {
      "min": 40000.0,
      "q1": 128000.0,
      "median": 156000.0,
      "q3": 189500.0,
      "max": 266500.0,
      "outliers": [
        315000.0,
        359100.0
      ],
      "n_outliers": 2,
      "category": "70",
      "n": 60
    },
    {
      "min": 75000.0,
      "q1": 114000.0,
      "median": 146000.0,
      "q3": 164850.0,
      "max": 239000.0,
      "outliers": [],
      "n_outliers": 0,
      "category": "160",
      "n": 63
    },
    {
      "min": 79500.0,
      "q1": 119625.0,
      "median": 142500.0,
      "q3": 179000.0,
      "max": 260000.0,
      "outliers": [],
      "n_outliers": 0,
      "category": "40",
      "n": 4
    },
    {
      "min": 123000.0,
      "q1": 134350.0,
      "median": 140750.0,
      "q3": 158375.0,
      "max": 178400.0,
      "outliers": [
        198500.0
      ],
      "n_outliers": 1,
      "category": "85",
      "n": 20
    },
    {
      "min": 82000.0,
      "q1": 118375.0,
      "median": 135980.0,
      "q3": 145000.0,
      "max": 179000.0,
      "outliers": [
        206300.0,
        188000.0,
        190000.0,
        200000.0
      ],
      "n_outliers": 4,
      "category": "90",
      "n": 52
    },
    {
      "min": 66500.0,
      "q1": 114125.0,
      "median": 132000.0,
      "q3": 159000.0,
      "max": 225000.0,
      "outliers": [
        239686.0,
        311500.0,
        277000.0,
        229000.0,
        316600.0,
        240000.0,
        250000.0,
        37900.0,
        285000.0,
        381000.0,
        256000.0,
        410000.0
      ],
      "n_outliers": 12,
      "category": "50",
      "n": 144
    },
    {
      "min": 80000.0,
      "q1": 108875.0,
      "median": 128250.0,
      "q3": 143750.0,
      "max": 168000.0,
      "outliers": [
        228950.0,
        200000.0,
        55000.0
      ],
      "n_outliers": 3,
      "category": "190",
      "n": 30
    },
    {
      "min": 76000.0,
      "q1": 94125.0,
      "median": 107500.0,
      "q3": 122250.0,
      "max": 139400.0,
      "outliers": [],
      "n_outliers": 0,
      "category": "45",
      "n": 12
    },
    {
      "min": 52000.0,
      "q1": 81000.0,
      "median": 99900.0,
      "q3": 110500.0,
      "max": 153500.0,
      "outliers": [
        163500.0,
        34900.0
      ],
      "n_outliers": 2,
      "category": "30",
      "n": 69
    },
    {
      "min": 75500.0,
      "q1": 81875.0,
      "median": 88500.0,
      "q3": 128000.0,
      "max": 148000.0,
      "outliers": [],
      "n_outliers": 0,
      "category": "180",
      "n": 10
    }
  ]
}